{
    "key": "group_60e99f05c40d2",
    "title": "POSTS – Cours",
    "fields": [
        {
            "key": "field_60e99f0a44649",
            "label": "Cours",
            "name": "classes",
            "type": "repeater",
            "instructions": "",
            "required": 0,
            "conditional_logic": 0,
            "wrapper": {
                "width": "",
                "class": "",
                "id": ""
            },
            "collapsed": "",
            "min": 0,
            "max": 0,
            "layout": "table",
            "button_label": "",
            "sub_fields": [
                {
                    "key": "field_60e99f1b4464a",
                    "label": "type",
                    "name": "type",
                    "type": "text",
                    "instructions": "",
                    "required": 0,
                    "conditional_logic": 0,
                    "wrapper": {
                        "width": "",
                        "class": "",
                        "id": ""
                    },
                    "default_value": "",
                    "placeholder": "",
                    "prepend": "",
                    "append": "",
                    "maxlength": ""
                },
                {
                    "key": "field_60e99f2f4464b",
                    "label": "Horaire",
                    "name": "time",
                    "type": "time_picker",
                    "instructions": "",
                    "required": 0,
                    "conditional_logic": 0,
                    "wrapper": {
                        "width": "",
                        "class": "",
                        "id": ""
                    },
                    "display_format": "G:i",
                    "return_format": "H:i"
                },
                {
                    "key": "field_60e99f484464c",
                    "label": "prof",
                    "name": "teacher",
                    "type": "text",
                    "instructions": "",
                    "required": 0,
                    "conditional_logic": 0,
                    "wrapper": {
                        "width": "",
                        "class": "",
                        "id": ""
                    },
                    "default_value": "",
                    "placeholder": "",
                    "prepend": "",
                    "append": "",
                    "maxlength": ""
                },
                {
                    "key": "field_60e99f564464d",
                    "label": "niveau",
                    "name": "level",
                    "type": "button_group",
                    "instructions": "",
                    "required": 0,
                    "conditional_logic": 0,
                    "wrapper": {
                        "width": "",
                        "class": "",
                        "id": ""
                    },
                    "choices": {
                        "1": "1",
                        "2": "2",
                        "3": "3"
                    },
                    "allow_null": 0,
                    "default_value": "",
                    "layout": "horizontal",
                    "return_format": "value"
                },
                {
                    "key": "field_60e99f744464e",
                    "label": "Jour",
                    "name": "day",
                    "type": "select",
                    "instructions": "",
                    "required": 0,
                    "conditional_logic": 0,
                    "wrapper": {
                        "width": "",
                        "class": "",
                        "id": ""
                    },
                    "choices": {
                        "lundi": "lundi",
                        "mardi": "mardi",
                        "mercredi": "mercredi",
                        "jeudi": "jeudi",
                        "vendredi": "vendredi",
                        "samedi": "samedi",
                        "dimanche": "dimanche"
                    },
                    "default_value": false,
                    "allow_null": 1,
                    "multiple": 0,
                    "ui": 1,
                    "ajax": 0,
                    "return_format": "value",
                    "placeholder": ""
                },
                {
                    "key": "field_60e99fb84464f",
                    "label": "Durée",
                    "name": "lenght",
                    "type": "text",
                    "instructions": "",
                    "required": 0,
                    "conditional_logic": 0,
                    "wrapper": {
                        "width": "",
                        "class": "",
                        "id": ""
                    },
                    "default_value": "",
                    "placeholder": "",
                    "prepend": "",
                    "append": "",
                    "maxlength": ""
                }
            ]
        }
    ],
    "location": [
        [
            {
                "param": "page_template",
                "operator": "==",
                "value": "template-classes.php"
            }
        ]
    ],
    "menu_order": 0,
    "position": "normal",
    "style": "default",
    "label_placement": "top",
    "instruction_placement": "label",
    "hide_on_screen": "",
    "active": true,
    "description": "",
    "modified": 1631273043
}